kuro2sudachi/__init__.py
kuro2sudachi/core.py
kuro2sudachi/normalizer.py
kuro2sudachi/rewrite.def
kuro2sudachi-0.4.7.dist-info/LICENCE
kuro2sudachi-0.4.7.dist-info/METADATA
kuro2sudachi-0.4.7.dist-info/WHEEL
kuro2sudachi-0.4.7.dist-info/entry_points.txt
kuro2sudachi-0.4.7.dist-info/RECORD
