Metadata-Version: 2.3
Name: kuro2sudachi
Version: 0.4.7
Summary: 
License: Apache-2.0
Author: po3rin
Requires-Python: >=3.11,<4.0
Classifier: License :: OSI Approved :: Apache Software License
Classifier: Programming Language :: Python :: 3
Classifier: Programming Language :: Python :: 3.11
Classifier: Programming Language :: Python :: 3.12
Classifier: Programming Language :: Python :: 3.13
Requires-Dist: importlib-metadata (>=6.7.0,<7.0.0)
Requires-Dist: jaconv (>=0.2.4,<0.3.0)
Requires-Dist: sudachidict-core (>=20250129,<20250130)
Requires-Dist: sudachidict-full (>=20250129,<20250130)
Requires-Dist: sudachipy (>=0.6.7,<0.7.0)
Project-URL: Homepage, http://github.com/po3rin/kuro2sudachi
Project-URL: Repository, http://github.com/po3rin/kuro2sudachi
